README.rst
setup.cfg
setup.py
cacpanel/__init__.py
cacpanel/cli.py
cacpanel/panel.py
cacpanel.egg-info/PKG-INFO
cacpanel.egg-info/SOURCES.txt
cacpanel.egg-info/dependency_links.txt
cacpanel.egg-info/entry_points.txt
cacpanel.egg-info/requires.txt
cacpanel.egg-info/top_level.txt