Metadata-Version: 1.1
Name: cacpanel
Version: 0.2.3
Summary: A python wrapper and CLI for the panel.cloudatcost.com https://panel.cloudatcost.com
Home-page: https://github.com/makefu/cac-panel
Author: makefu
Author-email: github@syntax-fehler.de
License: WTFPL
Keywords: panel.cloudatcost.com screen-scraper
Platform: UNKNOWN
Classifier: Intended Audience :: Developers
Classifier: Topic :: Software Development :: Libraries :: Python Modules
Classifier: Programming Language :: Python :: 2
Classifier: Programming Language :: Python :: 3
